netbox_demo/__init__.py
netbox_demo/forms.py
netbox_demo/signals.py
netbox_demo/urls.py
netbox_demo/utils.py
netbox_demo/views.py
netbox_demo/templates/netbox_demo/login.html
netbox_demo-0.4.0.dist-info/LICENSE.txt
netbox_demo-0.4.0.dist-info/METADATA
netbox_demo-0.4.0.dist-info/WHEEL
netbox_demo-0.4.0.dist-info/top_level.txt
netbox_demo-0.4.0.dist-info/RECORD
