Metadata-Version: 2.1
Name: netbox-demo
Version: 0.4.0
Summary: NetBox plugin for demo instances (not for production use)
License: 
License-File: LICENSE.txt
